LICENSE
MANIFEST.in
README.md
pyproject.toml
setup.cfg
setup.py
src/ans/__init__.py
src/ans/about.html
src/ans/config.py
src/ans/dependency.py
src/ans/download.py
src/ans/gui.py
src/ans/gui.qss
src/ans/main.py
src/ans/mseed2sac.py
src/ans/ncf2egf.py
src/ans/plot.py
src/ans/proc.py
src/ans/sac2ncf.py
src/ans.egg-info/PKG-INFO
src/ans.egg-info/SOURCES.txt
src/ans.egg-info/dependency_links.txt
src/ans.egg-info/entry_points.txt
src/ans.egg-info/requires.txt
src/ans.egg-info/top_level.txt
src/ans/data/FetchData-2018.337
src/ans/data/assets.afdesign
src/ans/data/datacenters_stations.dat
src/ans/data/dummy.sac
src/ans/data/images/about.svg
src/ans/data/images/about_hover.svg
src/ans/data/images/about_selected.svg
src/ans/data/images/add.svg
src/ans/data/images/add_hover.svg
src/ans/data/images/ans_logo.svg
src/ans/data/images/discard.svg
src/ans/data/images/discard_hover.svg
src/ans/data/images/download.svg
src/ans/data/images/download_hover.svg
src/ans/data/images/download_selected.svg
src/ans/data/images/menu.svg
src/ans/data/images/menu_hover.svg
src/ans/data/images/mseed2sac.svg
src/ans/data/images/mseed2sac_hover.svg
src/ans/data/images/mseed2sac_selected.svg
src/ans/data/images/ncf2egf.svg
src/ans/data/images/ncf2egf_hover.svg
src/ans/data/images/ncf2egf_selected.svg
src/ans/data/images/remove.svg
src/ans/data/images/remove_hover.svg
src/ans/data/images/revert.svg
src/ans/data/images/revert_hover.svg
src/ans/data/images/sac2ncf.svg
src/ans/data/images/sac2ncf_hover.svg
src/ans/data/images/sac2ncf_selected.svg
src/ans/data/images/save.svg
src/ans/data/images/save_hover.svg
src/ans/data/images/setting.svg
src/ans/data/images/setting_hover.svg
src/ans/data/images/setting_selected.svg
src/ans/data/images/terminal.svg
src/ans/data/images/terminal_hover.svg