Metadata-Version: 2.1
Name: ans
Version: 0.0.1
Summary: ambient noise seismology using python
Home-page: https://github.com/omid-b/ans
Author: omid-b
Author-email: omid.bagherpur@gmail.com
License: UNKNOWN
Platform: UNKNOWN
Classifier: Programming Language :: Python :: 3
Classifier: License :: OSI Approved :: GNU Lesser General Public License v3 or later (LGPLv3+)
Classifier: Operating System :: OS Independent
Requires-Python: !=3.10.*,!=3.11.*,!=3.7.*,!=3.9.*,>=3
License-File: LICENSE
